degrotesque.py
degrotesque-3.0.0.dist-info/LICENSE
degrotesque-3.0.0.dist-info/METADATA
degrotesque-3.0.0.dist-info/WHEEL
degrotesque-3.0.0.dist-info/entry_points.txt
degrotesque-3.0.0.dist-info/top_level.txt
degrotesque-3.0.0.dist-info/RECORD
