Metadata-Version: 2.1
Name: degrotesque
Version: 3.0.0
Summary: A web type setter
Home-page: http://degrotesque.readthedocs.org/
Download-URL: http://pypi.python.org/pypi/degrotesque
Author: dkrajzew
Author-email: d.krajzewicz@gmail.com
License: BSD
Project-URL: Documentation, https://degrotesque.readthedocs.io/
Project-URL: Source, https://github.com/dkrajzew/degrotesque
Project-URL: Tracker, https://github.com/dkrajzew/degrotesque/issues
Project-URL: Discussions, https://github.com/dkrajzew/degrotesque/discussions
Classifier: Development Status :: 5 - Production/Stable
Classifier: Environment :: Console
Classifier: Programming Language :: Python
Classifier: Programming Language :: Python :: 2.7
Classifier: Programming Language :: Python :: 3
Classifier: License :: OSI Approved :: BSD License
Classifier: Operating System :: OS Independent
Classifier: Intended Audience :: Developers
Classifier: Intended Audience :: Information Technology
Classifier: Intended Audience :: System Administrators
Classifier: Intended Audience :: Telecommunications Industry
Classifier: Topic :: Documentation
Classifier: Topic :: Software Development :: Libraries :: Python Modules
Classifier: Topic :: Software Development :: Localization
Classifier: Topic :: Text Processing :: Markup :: HTML
Classifier: Topic :: Other/Nonlisted Topic
Classifier: Topic :: Artistic Software
Requires-Python: >=2.7, <4
License-File: LICENSE
